PyNomad.cp310-win_amd64.pyd
PyNomadBBO-4.5.1.dist-info/LICENSE
PyNomadBBO-4.5.1.dist-info/METADATA
PyNomadBBO-4.5.1.dist-info/WHEEL
PyNomadBBO-4.5.1.dist-info/top_level.txt
PyNomadBBO-4.5.1.dist-info/RECORD
