Metadata-Version: 2.1
Name: PyNomadBBO
Version: 4.5.1
Summary: Python interface to Nomad 4
Home-page: https://github.com/bbopt/nomad
Author: Jan Provaznik and Christophe Tribes
Author-email: Jan Provaznik and Christophe Tribes <christophe.tribes@polymtl.ca>
Maintainer-email: Christophe Tribes <christophe.tribes@polymtl.ca>
Project-URL: Documentation, https://nomad-4-user-guide.readthedocs.io/
Project-URL: Repository, https://github.com/bbopt/nomad.git
Project-URL: Issues, https://github.com/bbopt/nomad/issues
Classifier: Programming Language :: Python :: 3
Classifier: Programming Language :: C++
Classifier: Operating System :: OS Independent
Requires-Python: >=3.8
License-File: LICENSE
